{
  "$schema": "https://vega.github.io/schema/vega-lite/v5.json",
  "description": "Countries Obesity Rate over time",
  "width": 800,
  "height": 800,
  "data": {
    "url": "https://raw.githubusercontent.com/arnav-bhalla/Data-Vis/main/NCD_country.csv"
  },
  "params": [
    {
      "name": "Country_selection",
      "bind": {
        "input": "select",
        "options": [
          "Afghanistan",
          "Albania",
          "Algeria",
          "Andorra",
          "Angola",
          "Antigua and Barbuda",
          "Argentina",
          "Armenia",
          "Australia",
          "Austria",
          "Azerbaijan",
          "Bahamas",
          "Bahrain",
          "Bangladesh",
          "Barbados",
          "Belarus",
          "Belgium",
          "Belize",
          "Benin",
          "Bhutan",
          "Bolivia",
          "Bosnia and Herzegovina",
          "Botswana",
          "Brazil",
          "Brunei",
          "Bulgaria",
          "Burkina Faso",
          "Burundi",
          "Cabo Verde",
          "Cambodia",
          "Cameroon",
          "Canada",
          "Central African Republic",
          "Chad",
          "Chile",
          "China",
          "Colombia",
          "Comoros",
          "Congo",
          "Costa Rica",
          "Croatia",
          "Cuba",
          "Cyprus",
          "Czech Republic",
          "Democratic Republic of the Congo",
          "Denmark",
          "Djibouti",
          "Dominica",
          "Dominican Republic",
          "East Timor",
          "Ecuador",
          "Egypt",
          "El Salvador",
          "Equatorial Guinea",
          "Eritrea",
          "Estonia",
          "Eswatini",
          "Ethiopia",
          "Fiji",
          "Finland",
          "France",
          "Gabon",
          "Gambia",
          "Georgia",
          "Germany",
          "Ghana",
          "Greece",
          "Grenada",
          "Guatemala",
          "Guinea",
          "Guinea-Bissau",
          "Guyana",
          "Haiti",
          "Honduras",
          "Hungary",
          "Iceland",
          "India",
          "Indonesia",
          "Iran",
          "Iraq",
          "Ireland",
          "Israel",
          "Italy",
          "Ivory Coast",
          "Jamaica",
          "Japan",
          "Jordan",
          "Kazakhstan",
          "Kenya",
          "Kiribati",
          "Kuwait",
          "Kyrgyzstan",
          "Laos",
          "Latvia",
          "Lebanon",
          "Lesotho",
          "Liberia",
          "Libya",
          "Liechtenstein",
          "Lithuania",
          "Luxembourg",
          "Madagascar",
          "Malawi",
          "Malaysia",
          "Maldives",
          "Mali",
          "Malta",
          "Marshall Islands",
          "Mauritania",
          "Mauritius",
          "Mexico",
          "Micronesia",
          "Moldova",
          "Monaco",
          "Mongolia",
          "Montenegro",
          "Morocco",
          "Mozambique",
          "Myanmar",
          "Namibia",
          "Nauru",
          "Nepal",
          "Netherlands",
          "New Zealand",
          "Nicaragua",
          "Niger",
          "Nigeria",
          "North Korea",
          "North Macedonia",
          "Norway",
          "Oman",
          "Pakistan",
          "Palau",
          "Palestine",
          "Panama",
          "Papua New Guinea",
          "Paraguay",
          "Peru",
          "Philippines",
          "Poland",
          "Portugal",
          "Qatar",
          "Romania",
          "Russia",
          "Rwanda",
          "Saint Kitts and Nevis",
          "Saint Lucia",
          "Saint Vincent and the Grenadines",
          "Samoa",
          "San Marino",
          "Sao Tome and Principe",
          "Saudi Arabia",
          "Senegal",
          "Serbia",
          "Seychelles",
          "Sierra Leone",
          "Singapore",
          "Slovakia",
          "Slovenia",
          "Solomon Islands",
          "Somalia",
          "South Africa",
          "South Korea",
          "South Sudan",
          "Spain",
          "Sri Lanka",
          "Sudan",
          "Suriname",
          "Sweden",
          "Switzerland",
          "Syria",
          "Tajikistan",
          "Tanzania",
          "Thailand",
          "Togo",
          "Tonga",
          "Trinidad and Tobago",
          "Tunisia",
          "Turkey",
          "Turkmenistan",
          "Tuvalu",
          "Uganda",
          "Ukraine",
          "United Arab Emirates",
          "United Kingdom",
          "United States",
          "Uruguay",
          "Uzbekistan",
          "Vanuatu",
          "Vatican City",
          "Venezuela",
          "Vietnam",
          "Yemen",
          "Zambia",
          "Zimbabwe"
        ],
        "name": "Country Selection: "
      }
    },
    {
      "name": "Sex_selection",
      "bind": {
        "input": "select",
        "options": ["Men", "Women"],
        "labels": ["Men", "Women"],
        "name": "Sex: "
      }
    }

  ],
  "transform": [
    { "filter": "Country_selection == null || datum.Country == Country_selection" },
    { "filter": "Sex_selection == null || datum.Sex == Sex_selection" }
  ],
  "encoding": {
    "x": { "field": "Year", "type": "temporal", "title": "Year" },
    "y": {
      "field": "Mean BMI",
      "type": "quantitative",
      "title": "Mean BMI",
      "scale": { "domain": [15, 35] } 
    },
    "color": { "field": "Country", "type": "nominal" , "legend" : null },
    "opacity": { "value": 1 }
  },
  "layer": [
    {
      "description": "transparent layer to make it easier to trigger selection",
      "mark": { "type": "line", "strokeWidth": 8, "stroke": "transparent" }
    },
    {
      "mark": "line"
    },
    {
      "encoding": {
        "x": { "aggregate": "max", "field": "Year" },
        "y": { "aggregate": { "argmax": "Year" }, "field": "Mean BMI" }
      },
      "layer": [
        {
          "mark": { "type": "circle" }
        },
        {
          "mark": { "type": "text", "align": "left", "dx": 4 },
          "encoding": { "text": { "field": "Country", "type": "nominal" }
          }
        }
      ]
    }
  ],
  "config": { "view": { "stroke": null } }
}
